{"stats":{"minecraft:used":{"minecraft:glass":27,"minecraft:light_blue_banner":14,"minecraft:dark_oak_planks":1,"luphieclutteredmod:luphie_fuschia_armchair":6,"minecraft:flowering_azalea":1,"luphieclutteredmod:luphie_flowering_purple_fence":4,"minecraft:torchflower":2,"minecraft:daylight_detector":4,"minecraft:crying_obsidian":8,"luphieclutteredmod:luphie_purple_plank_set_stairs":12,"minecraft:spruce_wood":32,"minecraft:lantern":21,"luphieclutteredmod:luphie_angry_bee_lamp":2,"luphieclutteredmod:luphie_cat_window":1,"minecraft:beacon":1,"luphieclutteredmod:luphie_flowering_pink_wood":5,"minecraft:flowering_azalea_leaves":11,"minecraft:sculk_sensor":4,"minecraft:soul_lantern":1,"luphieclutteredmod:luphie_purple_plank_set_slab":68,"minecraft:blue_banner":32,"luphieclutteredmod:luphie_blue_mushroom_trapdoor":101,"luphieclutteredmod:luphie_blue_mushroom_block":51,"luphieclutteredmod:luphie_purple_plank_set_fence":27,"minecraft:pink_petals":10,"minecraft:glow_berries":2,"minecraft:respawn_anchor":1,"luphieclutteredmod:luphie_blue_glowshroom_terrarium":1,"minecraft:redstone_lamp":6,"minecraft:hopper":1,"minecraft:twisting_vines":6,"minecraft:red_banner":11,"alexsmobs:animal_dictionary":1,"minecraft:sea_pickle":10,"minecraft:spruce_fence":10,"ribbits:swamp_lantern":10,"minecraft:dark_oak_door":2},"minecraft:custom":{"minecraft:time_since_rest":163456,"minecraft:sprint_one_cm":179823,"minecraft:walk_one_cm":310672,"minecraft:damage_taken":60,"minecraft:drop":3,"minecraft:inspect_hopper":4,"minecraft:damage_dealt":55,"minecraft:interact_with_beacon":1,"minecraft:fly_one_cm":402924,"minecraft:crouch_one_cm":9696,"minecraft:play_time":163456,"minecraft:bell_ring":3,"minecraft:sneak_time":5926,"minecraft:jump":471,"minecraft:leave_game":3,"minecraft:time_since_death":163456,"minecraft:walk_on_water_one_cm":243,"minecraft:total_world_time":163456,"minecraft:climb_one_cm":745,"minecraft:fall_one_cm":209},"minecraft:dropped":{"minecraft:lever":1,"minecraft:diamond_leggings":1,"luphieclutteredmod:luphie_pink_glass_cabinet":1},"minecraft:picked_up":{"minecraft:dark_oak_door":1,"mca:engagement_ring_rg":1,"luphieclutteredmod:luphie_steampunk_lamp":1,"minecraft:rotten_flesh":4,"minecraft:diamond_leggings":1,"luphieclutteredmod:luphie_blue_glowshroom_terrarium":1,"minecraft:lever":1,"luphieclutteredmod:luphie_pink_glass_cabinet":1,"minecraft:blue_banner":6,"minecraft:snowball":9}},"DataVersion":3465}